aipkgs_database/__init__.py
aipkgs_database/core.py
aipkgs_database/db_engine/helpers.py
aipkgs_database/helpers.py
aipkgs_database-1.0.4.dist-info/METADATA
aipkgs_database-1.0.4.dist-info/WHEEL
aipkgs_database-1.0.4.dist-info/RECORD
